xauth/__init__.py
xauth/apps.py
xauth/authentication.py
xauth/internal_settings.py
xauth/loaders.py
xauth/settings.py
xauth/urls.py
xauth/accounts/__init__.py
xauth/accounts/abstract_models.py
xauth/accounts/admin.py
xauth/accounts/apps.py
xauth/accounts/managers.py
xauth/accounts/models.py
xauth/accounts/permissions.py
xauth/accounts/serializers.py
xauth/accounts/views.py
xauth/accounts/migrations/0001_initial.py
xauth/accounts/migrations/__init__.py
xauth/accounts/mixins/__init__.py
xauth/accounts/mixins/models.py
xauth/accounts/token/__init__.py
xauth/accounts/token/generator.py
xauth/accounts/token/key.py
xauth/management/__init__.py
xauth/management/commands/__init__.py
xauth/management/commands/create_xauth_app.py
xauth/templates/xauth/email-request-password-reset.html
xauth/templates/xauth/email-request-password-reset.txt
xauth/templates/xauth/email-request-verification.html
xauth/templates/xauth/email-request-verification.txt
django_rest_xauth-3.0.0.dist-info/LICENSE
django_rest_xauth-3.0.0.dist-info/METADATA
django_rest_xauth-3.0.0.dist-info/WHEEL
django_rest_xauth-3.0.0.dist-info/top_level.txt
django_rest_xauth-3.0.0.dist-info/RECORD
