Metadata-Version: 2.1
Name: django-rest-xauth
Version: 3.0.0
Summary: A custom user-model based package with features ranging from JWT and Basic authentication to REST API end-points for signup, signin, email verification, password resetting and account activation.
Home-page: https://github.com/ajharry69/django-rest-xauth
Author: Orinda Harrison
Author-email: mitch@xently.com
License: MIT
Project-URL: Source, https://github.com/ajharry69/django-rest-xauth
Keywords: django django-rest-framework jwt-bearer-tokens basic-authentication encryption-decryption authorization authentication
Classifier: Development Status :: 5 - Production/Stable
Classifier: Environment :: Web Environment
Classifier: Framework :: Django
Classifier: Framework :: Django :: 3.0
Classifier: Intended Audience :: Developers
Classifier: License :: OSI Approved :: MIT License
Classifier: Programming Language :: Python
Classifier: Programming Language :: Python :: 3
Classifier: Programming Language :: Python :: 3.6
Classifier: Programming Language :: Python :: 3.7
Classifier: Programming Language :: Python :: 3.8
Classifier: Programming Language :: Python :: 3.9
Classifier: Programming Language :: Python :: 3.10
Classifier: Programming Language :: Python :: 3 :: Only
Classifier: Topic :: Software Development
Classifier: Topic :: Internet :: WWW/HTTP
Requires-Python: >=3.6
License-File: LICENSE
Requires-Dist: djangorestframework
Requires-Dist: jwcrypto (<1.4,>=1.3)
Requires-Dist: django-xently
